blockmetro/__init__.py
blockmetro/blockmetro.py
blockmetro-1.1.dist-info/LICENCE.txt
blockmetro-1.1.dist-info/METADATA
blockmetro-1.1.dist-info/WHEEL
blockmetro-1.1.dist-info/top_level.txt
blockmetro-1.1.dist-info/RECORD
